Metadata-Version: 2.1
Name: dash-autocomplete-input
Version: 0.0.7
Summary: Dash component wrapper for `react-autocomplete-input`
Author: Sergey Karpov <karpov.sv@gmail.com>
License: MIT
Classifier: Framework :: Dash
License-File: LICENSE
